AoikConsulWatcher-0.0.1.dist-info/METADATA
AoikConsulWatcher-0.0.1.dist-info/RECORD
AoikConsulWatcher-0.0.1.dist-info/WHEEL
AoikConsulWatcher-0.0.1.dist-info/entry_points.txt
AoikConsulWatcher-0.0.1.dist-info/top_level.txt
aoikconsulwatcher/__init__.py
aoikconsulwatcher/__main__.py
aoikconsulwatcher/config.py
aoikconsulwatcher/watcher.py
aoikconsulwatcherdep/__init__.py
aoikconsulwatcherdep/aoikimportutil.py
